alertmanager/__init__.py
alertmanager/cli.py
alertmanager/core/__init__.py
alertmanager/core/alert_manager.py
alertmanager/core/base_manager.py
alertmanager/core/sqlite_adapter.py
alertmanager/utils/__init__.py
alertmanager/utils/logger.py
evolvishub_alertmanager-0.2.0.dist-info/licenses/LICENSE
evolvishub_alertmanager-0.2.0.dist-info/METADATA
evolvishub_alertmanager-0.2.0.dist-info/WHEEL
evolvishub_alertmanager-0.2.0.dist-info/entry_points.txt
evolvishub_alertmanager-0.2.0.dist-info/top_level.txt
evolvishub_alertmanager-0.2.0.dist-info/RECORD
